listinfo/__init__.py
listinfo/listinfo11.py
listinfo-1.0.dist-info/LICENSE
listinfo-1.0.dist-info/METADATA
listinfo-1.0.dist-info/WHEEL
listinfo-1.0.dist-info/top_level.txt
listinfo-1.0.dist-info/RECORD
