Metadata-Version: 2.1
Name: listinfo
Version: 1.0
Summary: A lightweight library to get details of list and it helps to split list into lists of small size also it 
Author: SusmitPanda
Author-email: susmit.vssut@gmail.com
License: MIT
Keywords: lisinfo,list statistics,split list,list tochunks
Platform: UNKNOWN
Classifier: Development Status :: 3 - Alpha
Classifier: Intended Audience :: Developers
Classifier: Topic :: Software Development :: Build Tools
Classifier: License :: OSI Approved :: MIT License
Classifier: Programming Language :: Python :: 3
Classifier: Programming Language :: Python :: 3.4
Classifier: Programming Language :: Python :: 3.5
Classifier: Programming Language :: Python :: 3.6
Classifier: Programming Language :: Python :: 3.7
Classifier: Programming Language :: Python :: 3.8
Classifier: Programming Language :: Python :: 3.9
License-File: LICENSE
